{
	"class" : {
		 },
	"instance" : {
		"initialize" : "msc 5/15/2015 16:21",
		"isAdmin" : "msc 5/15/2015 16:37",
		"isAdmin:" : "msc 5/15/2015 16:38",
		"loginFailed" : "msc 5/19/2015 13:13",
		"logout" : "msc 5/19/2015 13:14",
		"renderCheckboxAdminOn:" : "msc 5/15/2015 16:36",
		"renderContentOn:" : "msc 5/19/2015 14:31",
		"renderInputUsernameOn:" : "msc 5/15/2015 16:28",
		"renderSubmitButtonOn:" : "msc 5/19/2015 13:37",
		"username" : "msc 5/15/2015 16:25",
		"username:" : "msc 5/15/2015 16:26",
		"validateLogin" : "msc 5/19/2015 13:55" } }
